[
  {
    "id": 217,
    "answer": "<h3>Definition</h3><p><strong>ES6 Modules</strong> are JavaScript's native module system using <code>import</code> and <code>export</code> statements. They let you split code into separate files, each exporting specific functions/classes, and import only what you need. Unlike CommonJS (<code>require</code>), ES6 modules are statically analyzable — bundlers like Vite can tree-shake unused exports.</p><h3>Concrete Use-Case</h3><p>In ContactsHub (React 18 + Vite), every component, hook, and utility is an ES6 module. The <code>ContactCard</code> component imports only <code>formatDate</code> from <code>utils.js</code>, not the entire utility library. Vite's tree-shaking removes unused exports from the production bundle.</p><h3>Code Example</h3><pre><code>// utils/date.js — Named exports\nexport const formatDate = (date) => new Intl.DateTimeFormat('en-IN').format(new Date(date));\nexport const isWeekend = (date) => [0, 6].includes(new Date(date).getDay());\nexport const daysBetween = (start, end) =>\n  Math.ceil((new Date(end) - new Date(start)) / (1000 * 60 * 60 * 24));\n\n// components/LeaveForm.jsx — Import only what's needed\nimport { isWeekend, daysBetween } from '../utils/date.js';\n// formatDate is NOT imported → tree-shaken from bundle\n\n// services/api.js — Default export\nexport default class ApiService {\n  async getLeaves() { return fetch('/api/leaves').then(r => r.json()); }\n}\n\n// Usage: import ApiService from '../services/api.js';</code></pre><h3>Key Differences from CommonJS</h3><table><tr><th>Feature</th><th>ES6 Modules</th><th>CommonJS (require)</th></tr><tr><td>Syntax</td><td><code>import/export</code></td><td><code>require/module.exports</code></td></tr><tr><td>Loading</td><td>Static (compile-time)</td><td>Dynamic (runtime)</td></tr><tr><td>Tree-shaking</td><td>Yes — bundlers remove unused exports</td><td>No — entire module loaded</td></tr><tr><td>Top-level await</td><td>Supported</td><td>Not supported</td></tr><tr><td>Where</td><td>Browsers + Node.js (.mjs / type:module)</td><td>Node.js only</td></tr></table><h3>Pitfall &amp; Mitigation</h3><p><strong>Pitfall:</strong> Mixing <code>import</code> and <code>require</code> in the same file. Node.js throws <code>ERR_REQUIRE_ESM</code> when you <code>require()</code> an ES module.</p><p><strong>Mitigation:</strong> Choose one system per project. For new projects, use ES modules (<code>\"type\": \"module\"</code> in package.json). For legacy, stick with CommonJS. Don't mix.</p>"
  },
  {
    "id": 218,
    "answer": "<h3>The Problem</h3><p>Before ES6 modules, JavaScript had no native way to organize code across files. Developers relied on: (1) global variables (collision risk), (2) IIFEs (verbose, hard to maintain), (3) CommonJS (Node.js only, not tree-shakeable), or (4) AMD/RequireJS (complex configuration). Each approach had significant drawbacks.</p><h3>What ES6 Modules Solve</h3><ul><li><strong>Code organization:</strong> Each file is a module with explicit imports/exports — no global namespace pollution</li><li><strong>Bundle optimization:</strong> Static imports enable tree-shaking. In ContactsHub, Vite eliminated 40% of dead code from the production bundle</li><li><strong>Circular dependency detection:</strong> Tools can statically analyze the import graph and warn about circular dependencies</li><li><strong>Lazy loading:</strong> Dynamic <code>import()</code> enables code splitting. In ContactsHub, the CSV upload modal loads only when the user clicks 'Import'</li></ul><h3>Real-World Impact</h3><p>In the CRM Dashboard (Angular 18), modules are used for lazy-loaded route modules. The deals page, leads page, and analytics page are separate Angular modules loaded on demand. Initial bundle shrank from 1.2MB to 450KB because users only download the code for the page they're viewing.</p><h3>Code Example</h3><pre><code>// Dynamic import for code splitting (ContactsHub)\nconst CSVImportModal = React.lazy(() => import('./components/CSVImportModal'));\n\n// Only loaded when user clicks Import button\n&lt;Suspense fallback={&lt;Spinner /&gt;}&gt;\n  {showImport && &lt;CSVImportModal onClose={() => setShowImport(false)} /&gt;}\n&lt;/Suspense&gt;\n\n// Angular lazy-loaded routes (CRM Dashboard)\nconst routes: Routes = [\n  { path: 'deals', loadChildren: () => import('./deals/deals.module').then(m => m.DealsModule) },\n  { path: 'leads', loadChildren: () => import('./leads/leads.module').then(m => m.LeadsModule) },\n];</code></pre><h3>Pitfall &amp; Mitigation</h3><p><strong>Pitfall:</strong> Circular dependencies between modules. Module A imports Module B, which imports Module A. This causes undefined imports at runtime.</p><p><strong>Mitigation:</strong> Use tools like <code>madge</code> to visualize the dependency graph. Extract shared logic into a third module that both A and B import.</p>"
  },
  {
    "id": 223,
    "answer": "<h3>Definition</h3><p>A <strong>closure</strong> is a function that remembers the variables from its outer scope even after the outer function has returned. The inner function 'closes over' the variables, keeping them alive in memory.</p><h3>Concrete Use-Case</h3><p>In ContactsHub, I use closures in the debounced search function — the timer variable is enclosed in the outer function's scope and persists across calls:</p><h3>Code Example</h3><pre><code>// Closure: debounce function\nfunction createDebounce(fn, delay) {\n  let timer; // This variable is 'closed over'\n  return function (...args) {\n    clearTimeout(timer);       // Access timer from outer scope\n    timer = setTimeout(() => { // Update timer from outer scope\n      fn.apply(this, args);\n    }, delay);\n  };\n}\n\n// Usage in ContactsHub search\nconst debouncedSearch = createDebounce(async (query) => {\n  const results = await fetch(`/api/contacts?q=${query}`);\n  setContacts(await results.json());\n}, 300);\n\n// Every keystroke calls debouncedSearch, but the API\n// is only called 300ms after the user stops typing.\n// The 'timer' variable persists between calls thanks to closure.\n\n// Another practical closure: createCounter\nfunction createCounter(initial = 0) {\n  let count = initial; // Private variable via closure\n  return {\n    increment: () => ++count,\n    decrement: () => --count,\n    getCount: () => count\n  };\n  // 'count' is private — no external code can modify it directly\n}\nconst counter = createCounter(10);\ncounter.increment(); // 11\ncounter.getCount();  // 11</code></pre><h3>Visual Flow</h3><svg viewBox='0 0 420 120' xmlns='http://www.w3.org/2000/svg' style='width:100%;max-width:420px;font-family:monospace;font-size:10px'><rect x='10' y='10' width='190' height='100' rx='6' fill='none' stroke='#a78bfa' stroke-dasharray='4'/><text x='105' y='28' fill='#c4b5fd' text-anchor='middle'>Outer Function Scope</text><rect x='20' y='35' width='80' height='25' rx='3' fill='#5b21b6'/><text x='60' y='52' fill='#e9d5ff' text-anchor='middle' font-size='9'>let timer</text><rect x='20' y='68' width='170' height='35' rx='4' fill='#2563eb'/><text x='105' y='83' fill='#fff' text-anchor='middle' font-size='9'>Inner Function (returned)</text><text x='105' y='96' fill='#93c5fd' text-anchor='middle' font-size='7'>Can access 'timer'</text><rect x='240' y='35' width='160' height='65' rx='4' fill='#065f46'/><text x='320' y='55' fill='#fff' text-anchor='middle' font-size='9'>After outer returns:</text><text x='320' y='72' fill='#86efac' text-anchor='middle' font-size='8'>'timer' still alive in</text><text x='320' y='86' fill='#86efac' text-anchor='middle' font-size='8'>inner function's closure</text><line x1='200' y1='85' x2='240' y2='67' stroke='#60a5fa' stroke-width='2'/></svg><h3>Pitfall &amp; Mitigation</h3><p><strong>Pitfall:</strong> Closures in loops with <code>var</code>. The classic interview trap: all callbacks share the same <code>i</code> variable.</p><pre><code>// BUG: All logs print 3\nfor (var i = 0; i < 3; i++) {\n  setTimeout(() => console.log(i), 100); // 3, 3, 3\n}\n// FIX: Use let (block-scoped) instead of var\nfor (let i = 0; i < 3; i++) {\n  setTimeout(() => console.log(i), 100); // 0, 1, 2\n}</code></pre><h3>Validation</h3><p><strong>Dev:</strong> Verify closure behavior by logging the closed-over variable at different points. Use Chrome DevTools Scope panel to inspect closure variables during debugging.</p>"
  },
  {
    "id": 224,
    "answer": "<h3>The Problem</h3><p>JavaScript needs a way to: (1) create private variables (no native <code>private</code> keyword in ES5), (2) maintain state across function calls without globals, (3) create factory functions that produce customized behavior. Without closures, you'd need global variables or class-based patterns for everything.</p><h3>What Closures Solve</h3><ul><li><strong>Data privacy:</strong> Variables enclosed in a closure are inaccessible from outside — true private state</li><li><strong>State persistence:</strong> The debounce timer in ContactsHub's search persists between keystrokes without being a global variable</li><li><strong>Function factories:</strong> Create specialized functions at runtime (e.g., a rate limiter per endpoint)</li><li><strong>Callbacks &amp; event handlers:</strong> Every callback function that references outer variables is a closure</li></ul><h3>Real-World Impact</h3><p>In the HR Leave System's Angular frontend, the HTTP interceptor uses a closure to track whether a token refresh is in progress. The <code>isRefreshing</code> boolean and the <code>refreshSubject</code> BehaviorSubject are closed over by the interceptor's methods, maintaining state across multiple concurrent API calls without polluting the global scope.</p><h3>Code Example</h3><pre><code>// Real use: API request wrapper with retry state (closure)\nfunction createApiClient(baseUrl) {\n  let retryCount = 0;         // Private via closure\n  let lastError = null;       // Private via closure\n  const MAX_RETRIES = 3;\n\n  return {\n    async fetch(path) {\n      try {\n        const res = await fetch(`${baseUrl}${path}`);\n        retryCount = 0; // Reset on success\n        return res.json();\n      } catch (err) {\n        lastError = err;\n        if (retryCount < MAX_RETRIES) {\n          retryCount++;\n          return this.fetch(path); // Retry with state preserved\n        }\n        throw new Error(`Failed after ${MAX_RETRIES} retries: ${err.message}`);\n      }\n    },\n    getRetryCount: () => retryCount,\n    getLastError: () => lastError\n  };\n}\n\nconst api = createApiClient('https://api.hr-system.com');\nawait api.fetch('/leaves'); // retryCount managed internally via closure</code></pre><h3>Pitfall &amp; Mitigation</h3><p><strong>Pitfall:</strong> Memory leaks from closures holding references to large objects (DOM elements, big arrays) that should be garbage collected.</p><p><strong>Mitigation:</strong> Set references to <code>null</code> when no longer needed. In event listeners, use <code>removeEventListener</code> to break the closure reference chain.</p>"
  },
  {
    "id": 229,
    "answer": "<h3>Definition</h3><p>A <strong>Promise</strong> is a JavaScript object representing a value that may not exist yet but will resolve (or fail) in the future. It has three states: <strong>pending</strong> (waiting), <strong>fulfilled</strong> (succeeded with a value), and <strong>rejected</strong> (failed with a reason). Promises replace nested callbacks (callback hell) with chainable <code>.then()</code> calls.</p><h3>Visual Flow</h3><svg viewBox='0 0 480 100' xmlns='http://www.w3.org/2000/svg' style='width:100%;max-width:480px;font-family:monospace;font-size:10px'><rect x='10' y='35' width='90' height='30' rx='4' fill='#92400e'/><text x='55' y='54' fill='#fde68a' text-anchor='middle' font-size='9'>PENDING</text><rect x='160' y='10' width='120' height='30' rx='4' fill='#065f46'/><text x='220' y='29' fill='#86efac' text-anchor='middle' font-size='9'>FULFILLED (value)</text><rect x='160' y='60' width='120' height='30' rx='4' fill='#991b1b'/><text x='220' y='79' fill='#fca5a5' text-anchor='middle' font-size='9'>REJECTED (error)</text><rect x='340' y='10' width='80' height='30' rx='4' fill='#2563eb'/><text x='380' y='29' fill='#fff' text-anchor='middle' font-size='9'>.then()</text><rect x='340' y='60' width='80' height='30' rx='4' fill='#7c3aed'/><text x='380' y='79' fill='#fff' text-anchor='middle' font-size='9'>.catch()</text><line x1='100' y1='42' x2='160' y2='25' stroke='#34d399' stroke-width='2'/><line x1='100' y1='58' x2='160' y2='75' stroke='#ef4444' stroke-width='2'/><line x1='280' y1='25' x2='340' y2='25' stroke='#60a5fa' stroke-width='2'/><line x1='280' y1='75' x2='340' y2='75' stroke='#a78bfa' stroke-width='2'/></svg><h3>Concrete Use-Case</h3><p>In ContactsHub, fetching contacts from the API returns a Promise. I chain <code>.then()</code> for data transformation and <code>.catch()</code> for error handling:</p><h3>Code Example</h3><pre><code>// Promise basics\nconst fetchContacts = (query) => {\n  return new Promise((resolve, reject) => {\n    fetch(`/api/contacts?q=${query}`)\n      .then(res => {\n        if (!res.ok) reject(new Error(`HTTP ${res.status}`));\n        return res.json();\n      })\n      .then(data => resolve(data))\n      .catch(err => reject(err));\n  });\n};\n\n// Promise.all — parallel API calls (HR dashboard)\nconst loadDashboard = async () => {\n  const [balance, pending, history] = await Promise.all([\n    fetch('/api/leaves/balance').then(r => r.json()),\n    fetch('/api/leaves/pending').then(r => r.json()),\n    fetch('/api/leaves/history').then(r => r.json())\n  ]);\n  // All 3 calls run in parallel — total time = slowest call, not sum\n};\n\n// Promise.allSettled — don't fail if one call fails\nconst results = await Promise.allSettled([\n  fetch('/api/leaves'),\n  fetch('/api/notifications'),\n  fetch('/api/analytics')  // This might fail\n]);\nresults.forEach(r => {\n  if (r.status === 'fulfilled') console.log(r.value);\n  else console.warn('Failed:', r.reason);\n});</code></pre><h3>Pitfall &amp; Mitigation</h3><p><strong>Pitfall:</strong> Unhandled promise rejections. If you don't <code>.catch()</code> a rejected promise, Node.js logs a warning and may crash the process in future versions.</p><p><strong>Mitigation:</strong> Always add <code>.catch()</code> at the end of promise chains, or use <code>try/catch</code> with <code>async/await</code>. Set a global handler: <code>process.on('unhandledRejection', (err) => logger.error(err))</code></p>"
  },
  {
    "id": 230,
    "answer": "<h3>The Problem</h3><p>Before Promises, asynchronous JavaScript relied on callbacks. Multiple sequential async operations created 'callback hell' — deeply nested, unreadable code. Error handling was inconsistent (some callbacks used error-first pattern, some didn't). There was no standard way to run async operations in parallel.</p><h3>What Promises Solve</h3><ul><li><strong>Callback hell:</strong> Flat <code>.then()</code> chains instead of nested callbacks</li><li><strong>Error propagation:</strong> One <code>.catch()</code> at the end handles errors from any step in the chain</li><li><strong>Parallel execution:</strong> <code>Promise.all()</code> runs multiple async operations concurrently</li><li><strong>Composition:</strong> Promises are values you can pass around, store in arrays, and compose</li></ul><h3>Real-World Impact</h3><p>In the HR Leave System dashboard, loading the page requires 5 API calls (leave balance, pending requests, team calendar, notifications, analytics). With callbacks, this would be 5 nested functions. With <code>Promise.all()</code>, all 5 calls run in parallel and complete in the time of the slowest call (~200ms) instead of sequentially (~1000ms).</p><h3>Code Example</h3><pre><code>// BEFORE: Callback hell\ngetUser(userId, (err, user) => {\n  if (err) return handleError(err);\n  getLeaves(user.id, (err, leaves) => {\n    if (err) return handleError(err);\n    getBalance(user.id, (err, balance) => {\n      if (err) return handleError(err);\n      render({ user, leaves, balance });\n    });\n  });\n});\n\n// AFTER: Promise chain\ngetUser(userId)\n  .then(user => Promise.all([user, getLeaves(user.id), getBalance(user.id)]))\n  .then(([user, leaves, balance]) => render({ user, leaves, balance }))\n  .catch(handleError); // One catch handles all errors\n\n// BEST: async/await (syntactic sugar over Promises)\nconst user = await getUser(userId);\nconst [leaves, balance] = await Promise.all([\n  getLeaves(user.id),\n  getBalance(user.id)\n]);</code></pre><h3>Pitfall &amp; Mitigation</h3><p><strong>Pitfall:</strong> Using <code>Promise.all()</code> when one failure shouldn't cancel everything. If the analytics API fails, the entire dashboard fails to load.</p><p><strong>Mitigation:</strong> Use <code>Promise.allSettled()</code> for non-critical parallel calls. It returns results for all promises regardless of individual failures. Show the dashboard with whatever data succeeded.</p>"
  },
  {
    "id": 235,
    "answer": "<h3>Definition</h3><p><strong>Async/Await</strong> is syntactic sugar over Promises that makes asynchronous code look and behave like synchronous code. <code>async</code> marks a function as returning a Promise; <code>await</code> pauses execution until the Promise resolves. It eliminates <code>.then()</code> chains while keeping all Promise benefits.</p><h3>Concrete Use-Case</h3><p>In the HR Leave System's Fastify API, every route handler is an async function. The leave submission handler awaits: validation → overlap check → balance check → create leave → send notification — each step reads top-to-bottom like synchronous code.</p><h3>Code Example</h3><pre><code>// Async/await in a real Fastify route handler\napp.post('/api/leaves', async (req, reply) => {\n  // Each await pauses until the Promise resolves\n  const employee = await fastify.prisma.employee.findUnique({\n    where: { id: req.user.id }\n  });\n\n  // Check for overlapping leaves\n  const overlap = await fastify.prisma.leave.findFirst({\n    where: {\n      employeeId: req.user.id,\n      status: { in: ['pending', 'approved'] },\n      startDate: { lte: new Date(req.body.endDate) },\n      endDate: { gte: new Date(req.body.startDate) }\n    }\n  });\n  if (overlap) return reply.code(409).send({ error: 'Dates overlap existing leave' });\n\n  // Check balance\n  const days = daysBetween(req.body.startDate, req.body.endDate);\n  if (employee.leaveBalance < days) {\n    return reply.code(400).send({ error: 'Insufficient leave balance' });\n  }\n\n  // Create leave request\n  const leave = await fastify.prisma.leave.create({\n    data: { ...req.body, employeeId: req.user.id, status: 'pending' }\n  });\n\n  // Notify manager (non-blocking)\n  io.to(`user:${employee.managerId}`).emit('leave:new-request', leave);\n\n  reply.code(201).send(leave);\n});\n\n// Parallel async operations with await + Promise.all\nconst [balance, pending, history] = await Promise.all([\n  getBalance(userId),\n  getPendingLeaves(userId),\n  getLeaveHistory(userId)\n]);</code></pre><h3>Pitfall &amp; Mitigation</h3><p><strong>Pitfall:</strong> Sequential awaits when parallel is possible. Waiting for each API call to finish before starting the next:</p><pre><code>// BAD: Sequential (slow)\nconst balance = await getBalance(userId);   // 100ms\nconst pending = await getPending(userId);   // 100ms\nconst history = await getHistory(userId);   // 100ms\n// Total: 300ms\n\n// GOOD: Parallel (fast)\nconst [balance, pending, history] = await Promise.all([\n  getBalance(userId), getPending(userId), getHistory(userId)\n]);\n// Total: 100ms (time of slowest call)</code></pre><h3>Validation</h3><p><strong>Dev:</strong> Always wrap <code>await</code> calls in try/catch for proper error handling. Never leave unhandled async rejections.</p>"
  },
  {
    "id": 236,
    "answer": "<h3>The Problem</h3><p>Promise chains (<code>.then().then().catch()</code>) are better than callbacks but still create visual noise and make error handling awkward. Complex flows with conditional logic, loops, or error recovery become hard to read with chained <code>.then()</code> calls.</p><h3>What Async/Await Solves</h3><ul><li><strong>Readability:</strong> Async code reads top-to-bottom like synchronous code</li><li><strong>Error handling:</strong> Standard <code>try/catch</code> instead of <code>.catch()</code> chains — same pattern as synchronous code</li><li><strong>Debugging:</strong> Stack traces show meaningful function names and line numbers (Promises often show anonymous callbacks)</li><li><strong>Conditional logic:</strong> <code>if/else</code> with <code>await</code> is natural; with <code>.then()</code> chains, conditionals require nested returns</li></ul><h3>Real-World Impact</h3><p>In the HR Leave System's approval flow, the handler needs to: verify the manager's role → fetch the leave request → check business rules → update status → deduct balance → notify employee. With <code>.then()</code> chains, this was 6 nested callbacks. With async/await, it's 6 sequential lines — each clearly readable.</p><h3>Code Example</h3><pre><code>// BEFORE: Promise chain with conditional logic\napp.post('/api/leaves/:id/approve', (req, res) => {\n  verifyManager(req.user.id)\n    .then(isManager => {\n      if (!isManager) return Promise.reject(new Error('Not a manager'));\n      return Leave.findById(req.params.id);\n    })\n    .then(leave => {\n      if (leave.status !== 'pending') return Promise.reject(new Error('Not pending'));\n      return Leave.update(leave.id, { status: 'approved' });\n    })\n    .then(updated => {\n      return Balance.deduct(updated.employeeId, updated.days)\n        .then(() => updated);\n    })\n    .then(updated => res.json(updated))\n    .catch(err => res.status(400).json({ error: err.message }));\n});\n\n// AFTER: Async/await — clear, readable, debuggable\napp.post('/api/leaves/:id/approve', async (req, reply) => {\n  try {\n    const isManager = await verifyManager(req.user.id);\n    if (!isManager) return reply.code(403).send({ error: 'Not a manager' });\n\n    const leave = await Leave.findById(req.params.id);\n    if (leave.status !== 'pending') return reply.code(400).send({ error: 'Not pending' });\n\n    const updated = await Leave.update(leave.id, { status: 'approved' });\n    await Balance.deduct(updated.employeeId, updated.days);\n\n    io.to(`user:${updated.employeeId}`).emit('leave:approved', updated);\n    reply.send(updated);\n  } catch (err) {\n    reply.code(500).send({ error: err.message });\n  }\n});</code></pre><h3>Pitfall &amp; Mitigation</h3><p><strong>Pitfall:</strong> Using <code>await</code> inside <code>Array.forEach()</code>. The loop doesn't wait for each async operation — all iterations fire simultaneously, often causing race conditions.</p><p><strong>Mitigation:</strong> Use <code>for...of</code> for sequential async iteration, or <code>Promise.all(arr.map(...))</code> for parallel.</p>"
  },
  {
    "id": 241,
    "answer": "<h3>Definition</h3><p><strong>Type Narrowing</strong> in TypeScript means refining a variable's type from a broad type to a more specific one using control flow checks. After a type guard (<code>typeof</code>, <code>instanceof</code>, <code>in</code>, or custom), TypeScript narrows the type within that block, enabling safe property access.</p><h3>Concrete Use-Case</h3><p>In the HR Leave System, the API can return different response shapes for success vs error. Type narrowing lets us safely handle both:</p><h3>Code Example</h3><pre><code>// API response types\ntype ApiSuccess&lt;T&gt; = { success: true; data: T };\ntype ApiError = { success: false; error: string; code: number };\ntype ApiResponse&lt;T&gt; = ApiSuccess&lt;T&gt; | ApiError;\n\n// Type narrowing with discriminated union\nasync function fetchLeaves(): Promise&lt;ApiResponse&lt;Leave[]&gt;&gt; {\n  const res = await fetch('/api/leaves');\n  if (!res.ok) return { success: false, error: res.statusText, code: res.status };\n  return { success: true, data: await res.json() };\n}\n\nconst result = await fetchLeaves();\nif (result.success) {\n  // TypeScript KNOWS result is ApiSuccess&lt;Leave[]&gt; here\n  console.log(result.data.length);  // ✅ Safe: data exists\n  // result.error — ❌ Error: Property 'error' doesn't exist\n} else {\n  // TypeScript KNOWS result is ApiError here\n  console.log(result.error);  // ✅ Safe: error exists\n  // result.data — ❌ Error: Property 'data' doesn't exist\n}\n\n// typeof narrowing\nfunction formatValue(value: string | number): string {\n  if (typeof value === 'string') {\n    return value.toUpperCase();   // ✅ String methods available\n  }\n  return value.toFixed(2);        // ✅ Number methods available\n}\n\n// Custom type guard\nfunction isLeave(item: Leave | Holiday): item is Leave {\n  return 'approver' in item;\n}\n\nif (isLeave(item)) {\n  console.log(item.approver.name);  // ✅ Narrowed to Leave\n}</code></pre><h3>Pitfall &amp; Mitigation</h3><p><strong>Pitfall:</strong> Using type assertions (<code>as</code>) instead of proper narrowing. <code>result as ApiSuccess</code> skips runtime checks — if the result is actually an error, you get a runtime crash accessing <code>.data</code>.</p><p><strong>Mitigation:</strong> Always use runtime checks (typeof, in, custom guards) for narrowing. Save <code>as</code> assertions only for cases where you've already verified the type externally.</p>"
  },
  {
    "id": 242,
    "answer": "<h3>The Problem</h3><p>TypeScript's type system is only as useful as its precision. When a variable can be <code>string | number | null</code>, you can't call string methods or number methods without first proving which type it actually is. Without narrowing, every property access requires a type assertion — which is unsafe and defeats the purpose of TypeScript.</p><h3>What Type Narrowing Solves</h3><ul><li><strong>Runtime safety:</strong> TypeScript ensures you check the type before using type-specific methods</li><li><strong>Eliminated null crashes:</strong> Narrowing <code>user | null</code> prevents the classic 'Cannot read property of null'</li><li><strong>API response handling:</strong> Safely distinguish between success responses, error responses, and loading states</li><li><strong>Exhaustive checks:</strong> TypeScript warns you if you miss a case in a union type</li></ul><h3>Real-World Impact</h3><p>In the HR Leave System (Angular + TypeScript), the leave status can be <code>'pending' | 'approved' | 'rejected' | 'cancelled'</code>. Type narrowing with switch statements ensures every status is handled in the UI. When we added a new 'escalated' status, TypeScript flagged every switch statement that didn't handle it — preventing runtime errors.</p><h3>Code Example</h3><pre><code>// Exhaustive switch with narrowing\ntype LeaveStatus = 'pending' | 'approved' | 'rejected' | 'cancelled';\n\nfunction getStatusColor(status: LeaveStatus): string {\n  switch (status) {\n    case 'pending': return '#fbbf24';  // yellow\n    case 'approved': return '#22c55e'; // green\n    case 'rejected': return '#ef4444'; // red\n    case 'cancelled': return '#94a3b8'; // gray\n    default:\n      const _exhaustive: never = status; // ❌ Error if a case is missing\n      return _exhaustive;\n  }\n}\n\n// Nullable type narrowing\nfunction getManagerName(employee: Employee): string {\n  // employee.manager is Manager | null\n  if (employee.manager === null) {\n    return 'No manager assigned';\n  }\n  // TypeScript knows manager is Manager (not null) here\n  return employee.manager.name;\n}</code></pre><h3>Pitfall &amp; Mitigation</h3><p><strong>Pitfall:</strong> Narrowing doesn't persist across async boundaries. After an <code>await</code>, TypeScript re-widens the type because the value might have changed.</p><p><strong>Mitigation:</strong> Store the narrowed value in a <code>const</code>: <code>const manager = employee.manager; if (manager) { await something(); console.log(manager.name); }</code></p>"
  },
  {
    "id": 247,
    "answer": "<h3>Definition</h3><p><strong>Generics</strong> in TypeScript let you write functions, classes, and interfaces that work with any type while preserving type safety. Instead of using <code>any</code> (which disables type checking), generics use a type parameter like <code>&lt;T&gt;</code> that gets filled in when you call the function.</p><h3>Concrete Use-Case</h3><p>In the HR Leave System, I created a generic API response wrapper. Instead of writing separate types for <code>LeaveResponse</code>, <code>EmployeeResponse</code>, and <code>AnalyticsResponse</code>, one generic type handles all of them with full type safety.</p><h3>Code Example</h3><pre><code>// Generic API response type\ninterface ApiResponse&lt;T&gt; {\n  data: T;\n  status: number;\n  message: string;\n}\n\n// Generic fetch function\nasync function apiFetch&lt;T&gt;(url: string): Promise&lt;ApiResponse&lt;T&gt;&gt; {\n  const res = await fetch(url);\n  const data: T = await res.json();\n  return { data, status: res.status, message: res.statusText };\n}\n\n// Usage — TypeScript infers the return type\ninterface Leave { id: number; startDate: string; status: string; }\ninterface Employee { id: number; name: string; role: string; }\n\nconst leaves = await apiFetch&lt;Leave[]&gt;('/api/leaves');\nleaves.data[0].startDate;  // ✅ TypeScript knows this is string\nleaves.data[0].foo;        // ❌ Error: Property 'foo' doesn't exist on Leave\n\nconst employee = await apiFetch&lt;Employee&gt;('/api/employees/1');\nemployee.data.role;  // ✅ TypeScript knows this is string\n\n// Generic with constraints\ninterface HasId { id: number; }\nfunction findById&lt;T extends HasId&gt;(items: T[], id: number): T | undefined {\n  return items.find(item => item.id === id);\n}\n\nconst leave = findById(leaves.data, 5);  // Returns Leave | undefined\nconst emp = findById([{ id: 1, name: 'Manoj' }], 1); // Returns {id,name} | undefined</code></pre><h3>Pitfall &amp; Mitigation</h3><p><strong>Pitfall:</strong> Over-using generics. Making every function generic when it only ever works with one type. This adds complexity with no benefit.</p><p><strong>Mitigation:</strong> Use generics when a function genuinely works with multiple types. If it only ever takes <code>Leave[]</code>, just type it as <code>Leave[]</code>. Add generics when you find yourself duplicating functions for different types.</p>"
  },
  {
    "id": 248,
    "answer": "<h3>The Problem</h3><p>Without generics, you either: (1) use <code>any</code> and lose all type safety, or (2) duplicate code for each type. In the HR Leave System, writing a separate <code>fetchLeaves()</code>, <code>fetchEmployees()</code>, <code>fetchAnalytics()</code> with identical logic but different types means maintaining 3 copies of the same fetch wrapper.</p><h3>What Generics Solve</h3><ul><li><strong>Code reuse:</strong> One <code>apiFetch&lt;T&gt;</code> function handles all entity types</li><li><strong>Type safety:</strong> The return type matches the type parameter — no <code>any</code> escape hatch</li><li><strong>Documentation:</strong> Generic types make function signatures self-documenting</li><li><strong>Autocompletion:</strong> IDE provides correct suggestions based on the type parameter</li></ul><h3>Real-World Impact</h3><p>In the CRM Dashboard's Angular services, I wrote a generic <code>CrudService&lt;T&gt;</code> base class. Instead of writing CRUD logic for Deal, Lead, Contact, and Activity separately, each entity service extends <code>CrudService</code> with its type. 4 entity services share one implementation — any bug fix applies to all.</p><h3>Code Example</h3><pre><code>// Angular generic CRUD service (CRM Dashboard)\n@Injectable()\nexport abstract class CrudService&lt;T extends { id: number }&gt; {\n  constructor(private http: HttpClient, private endpoint: string) {}\n\n  getAll(): Observable&lt;T[]&gt; {\n    return this.http.get&lt;T[]&gt;(this.endpoint);\n  }\n\n  getById(id: number): Observable&lt;T&gt; {\n    return this.http.get&lt;T&gt;(`${this.endpoint}/${id}`);\n  }\n\n  create(item: Omit&lt;T, 'id'&gt;): Observable&lt;T&gt; {\n    return this.http.post&lt;T&gt;(this.endpoint, item);\n  }\n\n  update(id: number, item: Partial&lt;T&gt;): Observable&lt;T&gt; {\n    return this.http.put&lt;T&gt;(`${this.endpoint}/${id}`, item);\n  }\n\n  delete(id: number): Observable&lt;void&gt; {\n    return this.http.delete&lt;void&gt;(`${this.endpoint}/${id}`);\n  }\n}\n\n// Entity-specific services — zero duplicated CRUD logic\n@Injectable({ providedIn: 'root' })\nexport class DealService extends CrudService&lt;Deal&gt; {\n  constructor(http: HttpClient) { super(http, '/api/deals'); }\n}\n\n@Injectable({ providedIn: 'root' })\nexport class LeadService extends CrudService&lt;Lead&gt; {\n  constructor(http: HttpClient) { super(http, '/api/leads'); }\n}</code></pre><h3>Pitfall &amp; Mitigation</h3><p><strong>Pitfall:</strong> Generic type constraints that are too loose. <code>&lt;T&gt;</code> without constraints allows any type, including types that don't have the properties your function accesses.</p><p><strong>Mitigation:</strong> Use <code>extends</code> to constrain: <code>&lt;T extends { id: number }&gt;</code> ensures every T has an <code>id</code> property.</p>"
  },
  {
    "id": 253,
    "answer": "<h3>Top 3 Utility Type Mistakes</h3><h3>Mistake 1: Using Partial&lt;T&gt; for Create DTOs</h3><p>Making all fields optional when creating an entity means TypeScript won't catch missing required fields. <code>Partial&lt;Employee&gt;</code> allows creating an employee without a name or email.</p><p><strong>Fix:</strong> Use <code>Omit</code> + <code>Partial</code> selectively:</p><pre><code>// BAD: All fields optional\ntype CreateEmployee = Partial&lt;Employee&gt;;\n\n// GOOD: Required fields explicit, optional where appropriate\ntype CreateEmployee = Omit&lt;Employee, 'id' | 'createdAt'&gt; &amp; {\n  department?: string; // Only this is truly optional\n};</code></pre><h3>Mistake 2: Overusing Pick/Omit Creating Hidden Coupling</h3><p>Everywhere in the code: <code>Pick&lt;Employee, 'name' | 'email' | 'role'&gt;</code>. When the Employee interface changes, you have to update every Pick/Omit usage. It's worse than defining separate types.</p><p><strong>Fix:</strong> Define named types once: <code>type EmployeeSummary = Pick&lt;Employee, 'name' | 'email' | 'role'&gt;</code> — use the named type everywhere. Change in one place.</p><h3>Mistake 3: Record&lt;string, any&gt; Defeating Type Safety</h3><p>Using <code>Record&lt;string, any&gt;</code> as a catch-all for dynamic objects. You've essentially created an untyped dictionary — TypeScript can't help you.</p><p><strong>Fix:</strong> Use specific value types: <code>Record&lt;LeaveType, number&gt;</code> for leave balances, <code>Record&lt;string, Leave[]&gt;</code> for grouped leaves. The more specific the value type, the more TypeScript can validate.</p><h3>Validation</h3><p><strong>Dev:</strong> Enable <code>strict: true</code> in tsconfig — it catches most utility type misuses at compile time.</p>"
  },
  {
    "id": 254,
    "answer": "<h3>Definition</h3><p><strong>Utility Types</strong> are built-in TypeScript helpers that transform existing types into new ones. Instead of rewriting interfaces for every use case (create, update, response), you derive them from a base type using <code>Partial</code>, <code>Pick</code>, <code>Omit</code>, <code>Required</code>, <code>Record</code>, and others.</p><h3>Essential Utility Types</h3><pre><code>interface Employee {\n  id: number;\n  name: string;\n  email: string;\n  role: 'employee' | 'manager' | 'hr';\n  department: string;\n  createdAt: Date;\n}\n\n// Partial&lt;T&gt; — All fields optional (for updates)\ntype UpdateEmployee = Partial&lt;Employee&gt;;\n// { id?: number; name?: string; email?: string; ... }\n\n// Pick&lt;T, K&gt; — Select specific fields\ntype EmployeeCard = Pick&lt;Employee, 'id' | 'name' | 'role'&gt;;\n// { id: number; name: string; role: 'employee' | 'manager' | 'hr' }\n\n// Omit&lt;T, K&gt; — Remove specific fields\ntype CreateEmployee = Omit&lt;Employee, 'id' | 'createdAt'&gt;;\n// { name: string; email: string; role: ...; department: string }\n\n// Record&lt;K, V&gt; — Create a dictionary type\ntype LeaveBalances = Record&lt;'casual' | 'sick' | 'earned', number&gt;;\n// { casual: number; sick: number; earned: number }\n\n// Required&lt;T&gt; — Make all fields required\ntype StrictEmployee = Required&lt;Partial&lt;Employee&gt;&gt;;\n\n// Readonly&lt;T&gt; — Make all fields immutable\ntype FrozenEmployee = Readonly&lt;Employee&gt;;\n// Attempting to modify any field → TypeScript error</code></pre><h3>Concrete Use-Case</h3><p>In the HR Leave System, the <code>Leave</code> interface has 10 fields. The create endpoint needs <code>Omit&lt;Leave, 'id' | 'status' | 'createdAt' | 'approvedBy'&gt;</code> (server sets these). The update endpoint needs <code>Partial&lt;Pick&lt;Leave, 'startDate' | 'endDate' | 'reason'&gt;&gt;</code> (only editable fields). No interface duplication.</p><h3>Pitfall &amp; Mitigation</h3><p><strong>Pitfall:</strong> Deeply nested utility types that become unreadable: <code>Partial&lt;Omit&lt;Required&lt;Pick&lt;Employee, ...&gt;&gt;, 'id'&gt;&gt;</code></p><p><strong>Mitigation:</strong> If the type becomes complex, extract it as a named type with a descriptive name. Readability matters more than cleverness.</p>"
  },
  {
    "id": 259,
    "answer": "<h3>Top 3 Decorator Mistakes</h3><h3>Mistake 1: Not Enabling experimentalDecorators</h3><p>TypeScript decorators require <code>experimentalDecorators: true</code> in tsconfig.json. Without it, you get cryptic syntax errors. Angular CLI sets this by default, but standalone TypeScript projects often forget it.</p><p><strong>Fix:</strong> Add to tsconfig: <code>{ \"compilerOptions\": { \"experimentalDecorators\": true, \"emitDecoratorMetadata\": true } }</code></p><h3>Mistake 2: Decorator Order Confusion</h3><p>Multiple decorators execute bottom-up (closest to the class first), but evaluate top-down. In Angular, putting <code>@Injectable()</code> after <code>@Component()</code> can cause DI issues.</p><p><strong>Fix:</strong> Follow framework conventions. Angular: <code>@Component</code> (or <code>@Injectable</code>) is always the outermost decorator. Custom decorators go below the framework decorator.</p><h3>Mistake 3: Heavy Logic in Decorators</h3><p>Putting API calls, database queries, or complex computations in decorators. They run at class definition time (when the file is imported), not when the method is called. This can cause unexpected startup behavior.</p><p><strong>Fix:</strong> Decorators should only add metadata or wrap functions. Expensive operations should happen at call time inside the wrapper function, not at decoration time.</p><pre><code>// BAD: Heavy work at decoration time\nfunction CacheResult(target, key, descriptor) {\n  const cache = await loadCacheFromRedis(); // ❌ Runs at import time!\n}\n\n// GOOD: Heavy work deferred to call time\nfunction CacheResult(target, key, descriptor) {\n  const original = descriptor.value;\n  descriptor.value = async function (...args) {\n    const cached = await redis.get(key); // ✅ Runs when method is called\n    if (cached) return JSON.parse(cached);\n    const result = await original.apply(this, args);\n    await redis.set(key, JSON.stringify(result));\n    return result;\n  };\n}</code></pre><h3>Validation</h3><p><strong>Dev:</strong> Write unit tests for custom decorators to verify they wrap behavior correctly and handle edge cases (null returns, errors).</p>"
  },
  {
    "id": 260,
    "answer": "<h3>Definition</h3><p><strong>Decorators</strong> are special functions that can modify classes, methods, properties, or parameters at definition time. They're TypeScript's way of adding metadata or wrapping behavior — widely used in Angular (<code>@Component</code>, <code>@Injectable</code>, <code>@Input</code>) and NestJS.</p><h3>Concrete Use-Case</h3><p>In the HR Leave System's Angular frontend, decorators are everywhere: <code>@Component</code> marks classes as Angular components, <code>@Injectable</code> marks services for dependency injection, <code>@Input</code> / <code>@Output</code> define component interfaces.</p><h3>Code Example</h3><pre><code>// Angular decorators in action\n@Component({\n  selector: 'app-leave-card',\n  templateUrl: './leave-card.component.html',\n  changeDetection: ChangeDetectionStrategy.OnPush\n})\nexport class LeaveCardComponent {\n  @Input() leave!: Leave;      // Receives data from parent\n  @Output() approve = new EventEmitter&lt;number&gt;(); // Emits events to parent\n}\n\n@Injectable({ providedIn: 'root' })\nexport class LeaveService {\n  constructor(private http: HttpClient) {}\n  getLeaves() { return this.http.get&lt;Leave[]&gt;('/api/leaves'); }\n}\n\n// Custom decorator: Logging method execution time\nfunction LogExecutionTime(target: any, key: string, descriptor: PropertyDescriptor) {\n  const original = descriptor.value;\n  descriptor.value = function (...args: any[]) {\n    const start = performance.now();\n    const result = original.apply(this, args);\n    // Handle both sync and async\n    if (result instanceof Promise) {\n      return result.then(val => {\n        console.log(`${key} took ${(performance.now() - start).toFixed(2)}ms`);\n        return val;\n      });\n    }\n    console.log(`${key} took ${(performance.now() - start).toFixed(2)}ms`);\n    return result;\n  };\n  return descriptor;\n}\n\n// Usage\nclass LeaveService {\n  @LogExecutionTime\n  async getLeaveBalance(userId: number) {\n    return await prisma.leaveBalance.findUnique({ where: { userId } });\n  }\n}</code></pre><h3>Pitfall &amp; Mitigation</h3><p><strong>Pitfall:</strong> Creating too many custom decorators. Each one is magic behavior that new developers have to understand. The code becomes framework-like with its own learning curve.</p><p><strong>Mitigation:</strong> Stick to framework-provided decorators. Only create custom decorators for truly cross-cutting concerns (logging, caching, auth). Keep them simple and well-documented.</p>"
  },
  {
    "id": 265,
    "answer": "<h3>Top 3 Error Boundaries in TypeScript Mistakes</h3><h3>Mistake 1: Not Typing Error State Properly</h3><p>Using <code>any</code> for the error parameter in catch blocks. TypeScript doesn't narrow caught errors — they're <code>unknown</code> by default (with <code>useUnknownInCatchVariables</code>).</p><p><strong>Fix:</strong> Narrow the error type before accessing properties:</p><pre><code>try {\n  await fetch('/api/leaves');\n} catch (err) {\n  // BAD: err is 'unknown', not 'Error'\n  // console.log(err.message); // ❌ TypeScript error\n\n  // GOOD: Narrow first\n  if (err instanceof Error) {\n    console.log(err.message); // ✅ Safe\n  } else {\n    console.log('Unknown error:', String(err));\n  }\n}</code></pre><h3>Mistake 2: React Error Boundaries Not Catching Async Errors</h3><p>React class-based error boundaries only catch errors during rendering, lifecycle methods, and constructors. They do NOT catch errors in event handlers, async code, or <code>setTimeout</code>.</p><p><strong>Fix:</strong> Combine error boundaries for render errors with <code>try/catch</code> for async operations. In ContactsHub, the error boundary catches component render failures, while each async operation has its own try/catch with user-facing error state.</p><h3>Mistake 3: Swallowing Errors Silently</h3><p>Catching errors and doing nothing — the operation fails but the user sees no feedback. Common in Angular's <code>catchError</code> operator when returning <code>EMPTY</code>.</p><p><strong>Fix:</strong> Every catch must either show a user-facing error message or log for developers:</p><pre><code>// Angular: Don't swallow errors\nthis.leaveService.getLeaves().pipe(\n  catchError(err => {\n    this.snackBar.open('Failed to load leaves', 'Retry'); // User feedback\n    console.error('Leave fetch failed:', err);            // Dev logging\n    return of([]);  // Return empty array so UI doesn't break\n  })\n);</code></pre><h3>Validation</h3><p><strong>Dev:</strong> Test error scenarios: API down, malformed response, network timeout. Verify user sees meaningful error messages, not blank screens.</p>"
  },
  {
    "id": 266,
    "answer": "<h3>Definition</h3><p><strong>Error Boundaries</strong> (in React) and <strong>error interceptors</strong> (in Angular) are patterns for catching and handling errors at the component/service level so they don't crash the entire application. In TypeScript, proper error typing ensures type-safe error handling throughout the app.</p><h3>Concrete Use-Case</h3><p>In ContactsHub (React 18), if the contact list component throws during render (e.g., unexpected null data), the error boundary catches it and shows a 'Something went wrong' fallback instead of a white screen. The rest of the app (sidebar, header) keeps working.</p><h3>Code Example</h3><pre><code>// React Error Boundary with TypeScript\nimport { Component, ErrorInfo, ReactNode } from 'react';\n\ninterface Props { children: ReactNode; fallback?: ReactNode; }\ninterface State { hasError: boolean; error: Error | null; }\n\nclass ErrorBoundary extends Component&lt;Props, State&gt; {\n  state: State = { hasError: false, error: null };\n\n  static getDerivedStateFromError(error: Error): State {\n    return { hasError: true, error };\n  }\n\n  componentDidCatch(error: Error, info: ErrorInfo) {\n    console.error('Error boundary caught:', error, info.componentStack);\n    // Send to error tracking service\n  }\n\n  render() {\n    if (this.state.hasError) {\n      return this.props.fallback || (\n        &lt;div className=\"error-fallback\"&gt;\n          &lt;h2&gt;Something went wrong&lt;/h2&gt;\n          &lt;button onClick={() => this.setState({ hasError: false })}&gt;\n            Try Again\n          &lt;/button&gt;\n        &lt;/div&gt;\n      );\n    }\n    return this.props.children;\n  }\n}\n\n// Usage in ContactsHub\n&lt;ErrorBoundary fallback={&lt;ContactListError /&gt;}&gt;\n  &lt;ContactList contacts={contacts} /&gt;\n&lt;/ErrorBoundary&gt;\n\n// Angular: Global error handler\n@Injectable()\nexport class GlobalErrorHandler implements ErrorHandler {\n  constructor(private snackBar: MatSnackBar) {}\n  handleError(error: unknown) {\n    if (error instanceof HttpErrorResponse) {\n      this.snackBar.open(`API Error: ${error.status}`, 'Dismiss');\n    } else if (error instanceof Error) {\n      this.snackBar.open(error.message, 'Dismiss');\n    }\n    console.error('Global error:', error);\n  }\n}</code></pre><h3>Pitfall &amp; Mitigation</h3><p><strong>Pitfall:</strong> One giant error boundary wrapping the entire app. A single component error hides all content behind a generic error screen.</p><p><strong>Mitigation:</strong> Use granular error boundaries. Wrap each major section (sidebar, content, header) separately. A failed analytics widget shouldn't hide the entire dashboard.</p>"
  },
  {
    "id": 271,
    "answer": "<h3>Definition</h3><p><strong>Runtime</strong> is when code actually executes (in the browser or Node.js). <strong>Compile-time</strong> is when TypeScript checks types and transpiles to JavaScript. TypeScript types exist only at compile-time — they're completely erased at runtime. Understanding this distinction is crucial for using TypeScript effectively.</p><h3>Key Differences</h3><table><tr><th>Aspect</th><th>Compile-time</th><th>Runtime</th></tr><tr><td>When</td><td><code>tsc</code> or build step</td><td>Browser / Node.js execution</td></tr><tr><td>TypeScript types</td><td>Checked and validated</td><td>Completely erased</td></tr><tr><td>Errors caught</td><td>Type mismatches, missing properties</td><td>API failures, null values, business logic</td></tr><tr><td>Tools</td><td>TypeScript compiler, IDE</td><td>try/catch, runtime validators</td></tr></table><h3>Code Example</h3><pre><code>// This interface exists at COMPILE-TIME only\ninterface Leave {\n  id: number;\n  startDate: string;\n  status: 'pending' | 'approved';\n}\n\n// TypeScript checks this at compile-time ✅\nconst leave: Leave = { id: 1, startDate: '2025-03-01', status: 'pending' };\n\n// BUT: API response has no type checking at runtime!\nconst response = await fetch('/api/leaves/1');\nconst data: Leave = await response.json(); // TypeScript trusts you here\n// If API returns { id: '1', status: 'unknown' }, NO runtime error from TypeScript!\n// data.id is actually a string, not number — but TypeScript doesn't know\n\n// FIX: Validate at runtime boundaries\nimport { z } from 'zod';\nconst LeaveSchema = z.object({\n  id: z.number(),\n  startDate: z.string(),\n  status: z.enum(['pending', 'approved'])\n});\n\nconst validated = LeaveSchema.parse(await response.json());\n// NOW: Throws at runtime if API response doesn't match the schema</code></pre><h3>Pitfall &amp; Mitigation</h3><p><strong>Pitfall:</strong> Trusting that <code>const data: Leave = await res.json()</code> guarantees type safety. It doesn't — the type assertion is compile-time only.</p><p><strong>Mitigation:</strong> Validate data at system boundaries (API responses, user input, file reads) using runtime validators like Zod, io-ts, or Fastify's JSON Schema.</p>"
  },
  {
    "id": 272,
    "answer": "<h3>The Problem</h3><p>Developers often confuse compile-time safety with runtime safety. TypeScript catches type errors during development, but once the code runs in the browser or Node.js, types are gone. An API that returns <code>{status: 'unknown'}</code> when your type expects <code>'pending' | 'approved'</code> won't be caught by TypeScript.</p><h3>What Understanding This Distinction Solves</h3><ul><li><strong>API boundary safety:</strong> Knowing to validate external data at runtime, not just at compile-time</li><li><strong>Debugging:</strong> Understanding why a TypeScript 'type-safe' app still crashes with 'Cannot read property of undefined'</li><li><strong>Library choice:</strong> Knowing when to use Zod/io-ts (runtime validation) vs TypeScript interfaces (compile-time only)</li><li><strong>Performance:</strong> Types add zero runtime overhead — they're erased during compilation</li></ul><h3>Real-World Impact</h3><p>In the HR Leave System, the Angular frontend typed the leave API response as <code>Leave[]</code>. One day, the backend deployed a change that made <code>endDate</code> nullable. TypeScript saw <code>endDate: string</code> and the template did <code>leave.endDate.split('-')</code>. Runtime crash: 'Cannot call split of null'. The fix: update the type to <code>endDate: string | null</code> AND add a null check in the template. TypeScript + runtime guard together.</p><h3>Code Example</h3><pre><code>// Runtime validation with Zod (used in Fastify routes)\nimport { z } from 'zod';\n\n// Define once — used for BOTH compile-time types AND runtime validation\nconst LeaveCreateSchema = z.object({\n  startDate: z.string().regex(/^\\d{4}-\\d{2}-\\d{2}$/),\n  endDate: z.string().regex(/^\\d{4}-\\d{2}-\\d{2}$/),\n  leaveType: z.enum(['casual', 'sick', 'earned']),\n  reason: z.string().max(500).optional()\n});\n\n// Extract TypeScript type from Zod schema (compile-time)\ntype LeaveCreate = z.infer&lt;typeof LeaveCreateSchema&gt;;\n\n// Validate at runtime\napp.post('/api/leaves', async (req, reply) => {\n  const parsed = LeaveCreateSchema.safeParse(req.body);\n  if (!parsed.success) {\n    return reply.code(400).send({ errors: parsed.error.issues });\n  }\n  // parsed.data is type-safe AND runtime-validated\n  const leave = await prisma.leave.create({ data: parsed.data });\n});</code></pre><h3>Pitfall &amp; Mitigation</h3><p><strong>Pitfall:</strong> Using <code>as</code> type assertions to silence TypeScript errors. This makes the compile-time check pass but doesn't fix the runtime issue.</p><p><strong>Mitigation:</strong> Never use <code>as</code> to bypass errors — fix the actual type mismatch. If data comes from an external source, validate it at runtime first.</p>"
  },
  {
    "id": 277,
    "answer": "<h3>The Problem</h3><p>When frontend and backend teams work with different API response assumptions, bugs appear at integration time. The Angular component expects <code>{ dealValue: number }</code>, but the API returns <code>{ deal_value: string }</code>. TypeScript can't catch this because API responses aren't type-checked at runtime.</p><h3>What Type-Safe API Clients Solve</h3><ul><li><strong>Contract enforcement:</strong> Frontend and backend share the same type definitions — changes are caught at compile time</li><li><strong>Autocompletion:</strong> IDE suggests correct field names and types when building API requests</li><li><strong>Refactoring safety:</strong> Renaming a field in the shared type immediately shows all affected code</li><li><strong>Documentation:</strong> Types serve as living API documentation</li></ul><h3>Real-World Impact</h3><p>In the HR Leave System, the Angular HttpClient is typed with generic response types. When I changed the leave response to include <code>approvalChain</code>, TypeScript immediately flagged every component that accessed the old flat <code>approverName</code> field. Without type-safe clients, these bugs would only surface in production.</p><h3>Code Example</h3><pre><code>// Shared types (could be a shared npm package)\ninterface Leave {\n  id: number;\n  startDate: string;\n  endDate: string;\n  status: 'pending' | 'approved' | 'rejected';\n  approvalChain: ApprovalStep[];\n}\n\ninterface ApprovalStep {\n  level: number;\n  approver: { id: number; name: string };\n  decision: 'pending' | 'approved' | 'rejected';\n  decidedAt: string | null;\n}\n\n// Angular typed HTTP service\n@Injectable({ providedIn: 'root' })\nexport class LeaveService {\n  constructor(private http: HttpClient) {}\n\n  getLeaves(): Observable&lt;Leave[]&gt; {\n    return this.http.get&lt;Leave[]&gt;('/api/leaves');\n  }\n\n  createLeave(data: Omit&lt;Leave, 'id' | 'status' | 'approvalChain'&gt;): Observable&lt;Leave&gt; {\n    return this.http.post&lt;Leave&gt;('/api/leaves', data);\n  }\n}\n\n// Component gets full autocompletion\nthis.leaveService.getLeaves().subscribe(leaves => {\n  leaves[0].approvalChain[0].approver.name; // ✅ Full autocomplete\n  leaves[0].approverName; // ❌ TypeScript error — caught before runtime\n});</code></pre><h3>Pitfall &amp; Mitigation</h3><p><strong>Pitfall:</strong> Types drift from actual API responses. The shared type says <code>number</code>, the API returns <code>string</code>. TypeScript is satisfied but runtime breaks.</p><p><strong>Mitigation:</strong> Generate types from the API schema (OpenAPI/Swagger). Or use runtime validation (Zod) at the API boundary in the frontend.</p>"
  },
  {
    "id": 278,
    "answer": "<h3>Top 3 Type-Safe API Client Mistakes</h3><h3>Mistake 1: Defining Types Only on Frontend</h3><p>The Angular app has perfect types, but they're written independently from the Fastify backend. When the backend changes a field name, the frontend types are stale — TypeScript gives a false sense of safety.</p><p><strong>Fix:</strong> Share types between frontend and backend. Options: (1) shared types folder in a monorepo, (2) generate types from OpenAPI spec, (3) use a tool like <code>ts-rest</code> that enforces contract at both ends.</p><h3>Mistake 2: Using <code>any</code> for API Responses</h3><p>Typing <code>HttpClient.get&lt;any&gt;('/api/leaves')</code> because you're 'too busy to define types'. Now every property access is unchecked — you might as well use JavaScript.</p><p><strong>Fix:</strong> Always type API calls: <code>this.http.get&lt;Leave[]&gt;('/api/leaves')</code>. Even if it takes 5 minutes to define the interface, it saves hours of debugging type mismatches.</p><h3>Mistake 3: Not Handling Error Responses in Types</h3><p>The API can return <code>{ data: Leave[] }</code> on success or <code>{ error: string }</code> on failure. But the type only covers the success case. When the API returns an error, code tries to access <code>.data</code> on the error object → crash.</p><p><strong>Fix:</strong> Use discriminated unions:</p><pre><code>type ApiResult&lt;T&gt; =\n  | { success: true; data: T }\n  | { success: false; error: string; code: number };\n\nasync function getLeaves(): Promise&lt;ApiResult&lt;Leave[]&gt;&gt; {\n  try {\n    const res = await fetch('/api/leaves');\n    if (!res.ok) return { success: false, error: res.statusText, code: res.status };\n    return { success: true, data: await res.json() };\n  } catch (err) {\n    return { success: false, error: 'Network error', code: 0 };\n  }\n}</code></pre><h3>Validation</h3><p><strong>Dev:</strong> Run TypeScript in strict mode. Any <code>any</code> usage should be flagged in code review. <strong>Prod:</strong> Log API response shape mismatches to catch type drift early.</p>"
  },
  {
    "id": 283,
    "answer": "<h3>The Problem</h3><p>Without a properly configured <code>tsconfig.json</code>, TypeScript either: (1) is too lenient (allows <code>any</code>, implicit nulls, unchecked types) — defeating the purpose of TypeScript, or (2) is too strict for your project's stage — causing 500+ errors that slow development. The default config is a compromise that fits nobody perfectly.</p><h3>What TS Config Solves</h3><ul><li><strong>Strictness level:</strong> Controls how rigorous type checking is (<code>strict: true</code> enables all strict checks)</li><li><strong>Module system:</strong> Configures import/export behavior (CommonJS vs ESM)</li><li><strong>Build target:</strong> Which JavaScript version to output (ES2020 for Node.js, ES2015+ for browsers)</li><li><strong>Path aliases:</strong> <code>@components/Button</code> instead of <code>../../../components/Button</code></li><li><strong>Project structure:</strong> What to include/exclude from compilation</li></ul><h3>Real-World Impact</h3><p>In the HR Leave System (Angular 18), the Angular CLI generates a pre-configured tsconfig with strict mode. This caught several bugs during development: implicit <code>any</code> on HTTP responses, nullable fields accessed without checks, and missing return types on service methods. Each would have been a runtime bug without strict TS config.</p><h3>Code Example</h3><pre><code>// tsconfig.json for a Fastify + Prisma backend\n{\n  \"compilerOptions\": {\n    \"target\": \"ES2022\",\n    \"module\": \"commonjs\",\n    \"strict\": true,              // Enables all strict checks\n    \"esModuleInterop\": true,     // Allow default imports from CJS\n    \"outDir\": \"./dist\",\n    \"rootDir\": \"./src\",\n    \"resolveJsonModule\": true,   // Import JSON files\n    \"skipLibCheck\": true,\n    \"forceConsistentCasingInFileNames\": true,\n    \"paths\": {\n      \"@modules/*\": [\"./src/modules/*\"],\n      \"@shared/*\": [\"./src/shared/*\"]\n    }\n  },\n  \"include\": [\"src/**/*\"],\n  \"exclude\": [\"node_modules\", \"dist\", \"**/*.test.ts\"]\n}</code></pre><h3>Pitfall &amp; Mitigation</h3><p><strong>Pitfall:</strong> Setting <code>strict: false</code> to avoid fixing type errors, then never turning it on. The codebase grows with thousands of implicit <code>any</code> types, making it nearly impossible to enable strict later.</p><p><strong>Mitigation:</strong> Start every new project with <code>strict: true</code>. For existing projects, enable strict flags incrementally: <code>noImplicitAny</code> first, then <code>strictNullChecks</code>, then the rest.</p>"
  },
  {
    "id": 284,
    "answer": "<h3>Top 3 TS Config Mistakes</h3><h3>Mistake 1: Using strict: false in New Projects</h3><p>Starting with lenient config means the codebase accumulates implicit <code>any</code> types everywhere. By the time you enable strict mode, there are 2000+ errors. In the CRM Dashboard, we started without <code>strictNullChecks</code>. Enabling it later revealed 200+ potential null-access bugs that had been silently compiling.</p><p><strong>Fix:</strong> Always start new projects with <code>\"strict\": true</code>. Angular CLI does this by default. For Fastify backends, add it from day one.</p><h3>Mistake 2: Wrong Target/Module Configuration</h3><p>Setting <code>\"target\": \"ES5\"</code> for a Node.js 18+ backend. You lose native async/await, optional chaining, and other modern features. Or setting <code>\"module\": \"ESNext\"</code> for a CommonJS project — imports break.</p><p><strong>Fix:</strong> Match your runtime:</p><pre><code>// Node.js 18+ backend\n\"target\": \"ES2022\", \"module\": \"commonjs\"\n\n// Angular frontend (CLI manages this)\n\"target\": \"ES2022\", \"module\": \"ES2022\"\n\n// React + Vite (ESM)\n\"target\": \"ES2020\", \"module\": \"ESNext\", \"moduleResolution\": \"bundler\"</code></pre><h3>Mistake 3: Not Using Path Aliases</h3><p>Imports look like <code>import { LeaveService } from '../../../modules/leave/leave.service'</code>. When you move a file, every relative import breaks. Refactoring becomes a nightmare.</p><p><strong>Fix:</strong> Configure path aliases in tsconfig:</p><pre><code>\"paths\": {\n  \"@modules/*\": [\"./src/modules/*\"],\n  \"@shared/*\": [\"./src/shared/*\"]\n}\n// Now: import { LeaveService } from '@modules/leave/leave.service';\n// Move the file? Only update the path alias mapping, not every import.</code></pre><h3>Validation</h3><p><strong>Dev:</strong> Run <code>tsc --noEmit</code> in CI to catch type errors before merging. Add it as a pre-commit hook or GitHub Actions step.</p>"
  }
]
